kimmdy/__init__.py
kimmdy/analysis.py
kimmdy/cmd.py
kimmdy/config.py
kimmdy/constants.py
kimmdy/coordinates.py
kimmdy/kimmdy-yaml-schema.json
kimmdy/kmc.py
kimmdy/parsing.py
kimmdy/plugin_utils.py
kimmdy/plugins.py
kimmdy/py.typed
kimmdy/recipe.py
kimmdy/runmanager.py
kimmdy/schema.py
kimmdy/tasks.py
kimmdy/tools.py
kimmdy/utils.py
kimmdy/assets/templates.py
kimmdy/topology/__init__.py
kimmdy/topology/atomic.py
kimmdy/topology/ff.py
kimmdy/topology/topology.py
kimmdy/topology/utils.py
kimmdy-8.2.1.dist-info/licenses/LICENSE
kimmdy-8.2.1.dist-info/METADATA
kimmdy-8.2.1.dist-info/WHEEL
kimmdy-8.2.1.dist-info/entry_points.txt
kimmdy-8.2.1.dist-info/top_level.txt
kimmdy-8.2.1.dist-info/RECORD
