Metadata-Version: 2.4
Name: kimmdy
Version: 8.2.1
Summary: Kinetic Monte Carlo Molecular Dynamics
Author-email: graeter-group <mbm@h-its.org>
Classifier: Programming Language :: Python :: 3
Classifier: Operating System :: OS Independent
Requires-Python: <3.12,>=3.10
License-File: LICENSE
Requires-Dist: pyyaml
Requires-Dist: numpy
Requires-Dist: importlib_metadata
Requires-Dist: MDAnalysis
Provides-Extra: dimerization
Requires-Dist: kimmdy-dimerization; extra == "dimerization"
Provides-Extra: grappa
Requires-Dist: kimmdy-grappa; extra == "grappa"
Requires-Dist: grappa-ff; extra == "grappa"
Requires-Dist: torch; extra == "grappa"
Provides-Extra: hat
Requires-Dist: kimmdy-hat; extra == "hat"
Provides-Extra: hydrolysis
Requires-Dist: kimmdy-hydrolysis; extra == "hydrolysis"
Provides-Extra: reactions
Requires-Dist: kimmdy-reactions; extra == "reactions"
Provides-Extra: plugins
Requires-Dist: kimmdy-dimerization; extra == "plugins"
Requires-Dist: kimmdy-reactions; extra == "plugins"
Requires-Dist: kimmdy-grappa; extra == "plugins"
Requires-Dist: kimmdy-hat; extra == "plugins"
Requires-Dist: grappa-ff; extra == "plugins"
Requires-Dist: torch; extra == "plugins"
Requires-Dist: kimmdy-hydrolysis; extra == "plugins"
Provides-Extra: analysis
Requires-Dist: pandas; extra == "analysis"
Requires-Dist: matplotlib; extra == "analysis"
Requires-Dist: seaborn; extra == "analysis"
Dynamic: license-file
